pydala/__init__.py
pydala/catalog.py
pydala/catalog2.py
pydala/constants.py
pydala/dataset.py
pydala/filesystem.py
pydala/io.py
pydala/metadata.py
pydala/optimize.py
pydala/schema.py
pydala/sync.py
pydala/table.py
pydala/helpers/__init__.py
pydala/helpers/datetime.py
pydala/helpers/misc.py
pydala/helpers/polars.py
pydala/helpers/polars_ext.py
pydala/helpers/security.py
pydala/helpers/sql.py
pydala2-0.22.5.dist-info/METADATA
pydala2-0.22.5.dist-info/WHEEL
pydala2-0.22.5.dist-info/licenses/LICENSE
pydala2-0.22.5.dist-info/RECORD
