Metadata-Version: 2.3
Name: pydala2
Version: 0.22.5
Summary: poor man´s data lake
Author-email: "Volker L." <ligno.blades@gmail.com>
License: MIT
Requires-Python: >=3.11
Requires-Dist: brotli>=1.1.0
Requires-Dist: duckdb>=0.10.0
Requires-Dist: fsspec-utils[full]>=0.1.10
Requires-Dist: joblib>=1.3.2
Requires-Dist: loguru>=0.7.2
Requires-Dist: munch>=4.0.0
Requires-Dist: orjson>=3.10.12
Requires-Dist: pandas>=2.0.3
Requires-Dist: pendulum>=2.1.2
Requires-Dist: psutil>=6.0.0
Requires-Dist: pyarrow>=12.0.1
Requires-Dist: pyyaml>=6.0.2
Requires-Dist: s3fs>=2023.6.0
Requires-Dist: sqlglot>=23.11.2
Requires-Dist: sqlparse>=0.5.0
Requires-Dist: tqdm>=4.65.0
Provides-Extra: legacy
Requires-Dist: polars-lts-cpu>=0.20.4; extra == 'legacy'
Provides-Extra: standard
Requires-Dist: polars>=0.20.4; extra == 'standard'
